{
  "projects": [
    {
      "id": "abc123",
      "name": "Tau Tao",
      "rootIds": [
        {
          "id": "Xy6k8xK",
          "model": "items"
        },
        {
          "id": "YHnJKbd",
          "model": "items"
        }
      ],
      "goal": "My goal is to make a task manager that can persist data.",
      "strategy": "This would be cool. and it still is.",
      "velocity": "3"
    }
  ],
  "items": [
    {
      "name": "seed",
      "id": "usestringids"
    },
    {
      "name": "dddss",
      "id": "VZO5C1-"
    },
    {
      "name": "eeee",
      "id": "egPrL7Q"
    },
    {
      "name": "More",
      "points": "4",
      "id": "Xy6k8xK"
    },
    {
      "name": "morestuff",
      "points": "3",
      "id": "YHnJKbd"
    }
  ]
}